repr_llm/Untitled-1.ipynb
repr_llm/__init__.py
repr_llm/display.py
repr_llm/formatter.py
repr_llm/pandas.py
repr_llm-0.3.0.dist-info/LICENSE
repr_llm-0.3.0.dist-info/METADATA
repr_llm-0.3.0.dist-info/WHEEL
repr_llm-0.3.0.dist-info/RECORD
