Metadata-Version: 2.1
Name: repr-llm
Version: 0.3.0
Summary: Creating lightweight representations of objects for Large Language Model consumption
License: BSD-3-Clause
Author: Kyle Kelley
Author-email: rgbkrk@gmail.com
Requires-Python: >=3.9,<4.0
Classifier: License :: OSI Approved :: BSD License
Classifier: Programming Language :: Python :: 3
Classifier: Programming Language :: Python :: 3.9
Classifier: Programming Language :: Python :: 3.10
Classifier: Programming Language :: Python :: 3.11
Provides-Extra: dev
Provides-Extra: numfocus
Requires-Dist: ipython (>=7.0.0,<9.0.0) ; extra == "dev"
Requires-Dist: numpy[numfocus] (>=1.16.0) ; extra == "numfocus" or extra == "dev"
Requires-Dist: pandas[numfocus] (>=1.0.0,<3.0.0) ; extra == "numfocus" or extra == "dev"
Requires-Dist: tabulate[numfocus] (>=0.8.3,<0.10.0) ; extra == "dev"
